MeowerBot/__init__.py
MeowerBot/_cache.py
MeowerBot/_version.py
MeowerBot/api/__init__.py
MeowerBot/api/admin.py
MeowerBot/api/admin.pyi
MeowerBot/api/chats.py
MeowerBot/api/chats.pyi
MeowerBot/api/shared.py
MeowerBot/api/user.py
MeowerBot/bot.py
MeowerBot/cl/__init__.py
MeowerBot/cog.py
MeowerBot/command.py
MeowerBot/context.py
MeowerBot/data/__init__.py
MeowerBot/data/api/__init__.py
MeowerBot/data/api/chats.py
MeowerBot/data/api/reports.py
MeowerBot/data/api/user.py
MeowerBot/data/generic.py
MeowerBot/ext/help.py
meowerbot-3.3.2.dist-info/LICENSE
meowerbot-3.3.2.dist-info/METADATA
meowerbot-3.3.2.dist-info/WHEEL
meowerbot-3.3.2.dist-info/RECORD
